<?xml version="1.0" encoding="windows-1252" ?>
<!DOCTYPE ViewObject SYSTEM "jbo_03_01.dtd">
<!---->
<ViewObject
  xmlns="http://xmlns.oracle.com/bc4j"
  Name="POExchargesView"
  Version="11.1.2.64.36"
  SelectList="R5extcharges.ECH_CODE, 
       R5extcharges.ECH_DISCOUNT, 
       R5extcharges.ECH_DISCPERC, 
       R5extcharges.ECH_ID, 
       R5extcharges.ECH_INVORD, 
       R5extcharges.ECH_INVORD_CODE, 
       R5extcharges.ECH_INVORD_LINE, 
       R5extcharges.ECH_INVORD_ORG, 
       R5extcharges.ECH_PARPRICE, 
       R5extcharges.ECH_RTYPE, 
       R5extcharges.ECH_TYPE"
  FromList="MP5PRD.R5EXTCHARGES R5extcharges"
  BindingStyle="OracleName"
  CustomQuery="false"
  RowClass="its.mnr.mp5.baseclass.ExtendedViewRowImpl"
  ComponentClass="its.mnr.mp5.baseclass.ExtendedViewObjectImpl"
  DefClass="its.mnr.mp5.baseclass.ExtendedViewDefImpl"
  PageIterMode="Full"
  UseGlueCode="false"
  FetchMode="FETCH_AS_NEEDED"
  Passivate="All"
  OrderBy="R5extcharges.ECH_CODE">
  <Properties>
    <SchemaBasedProperties>
      <LABEL
        ResId="its.mnr.mp5.vo.po.POExchargesView_LABEL"/>
    </SchemaBasedProperties>
  </Properties>
  <ViewAccessor
    Name="UCodesLOV"
    ViewObjectName="its.mnr.mp5.lov.UCodesLOV"
    RowLevelBinds="true">
    <ViewCriteriaUsage
      Name="XChargesType"
      FullName="its.mnr.mp5.lov.UCodesLOV.XChargesType"/>
  </ViewAccessor>
  <ListBinding
    Name="LOV_EchType"
    ListVOName="UCodesLOV"
    ListRangeSize="-1"
    NullValueFlag="start"
    NullValueId="${adfBundle['oracle.javatools.resourcebundle.SystemBundle']['NULL_VALUE_RESID']}"
    MRUCount="0">
    <AttrArray Name="AttrNames">
      <Item Value="EchType"/>
    </AttrArray>
    <AttrArray Name="DerivedAttrNames">
      <Item Value="tTypeDesc"/>
    </AttrArray>
    <AttrArray Name="ListAttrNames">
      <Item Value="UcoCode"/>
      <Item Value="UcoDesc"/>
    </AttrArray>
    <AttrArray Name="ListDisplayAttrNames">
      <Item Value="UcoCode"/>
      <Item Value="UcoDesc"/>
    </AttrArray>
    <DisplayCriteria/>
  </ListBinding>
  <EntityUsage
    Name="R5extcharges"
    Entity="its.mnr.mp5.eo.local.R5extcharges"/>
  <ViewAttribute
    Name="EchCode"
    PrecisionRule="true"
    EntityAttrName="EchCode"
    EntityUsage="R5extcharges"
    AliasName="ECH_CODE"
    IsUpdateable="while_insert">
    <TransientExpression><![CDATA[(object.getRowSet().max("EchCode") == null ? 1 : object.getRowSet().max("EchCode")+ 1)]]></TransientExpression>
    <Properties>
      <SchemaBasedProperties>
        <LABEL
          ResId="its.mnr.mp5.vo.po.POExchargesView.EchCode_LABEL"/>
      </SchemaBasedProperties>
    </Properties>
  </ViewAttribute>
  <ViewAttribute
    Name="EchDiscount"
    PrecisionRule="true"
    EntityAttrName="EchDiscount"
    EntityUsage="R5extcharges"
    AliasName="ECH_DISCOUNT">
    <Properties>
      <SchemaBasedProperties>
        <LABEL
          ResId="its.mnr.mp5.vo.po.POExchargesView.EchDiscount_LABEL"/>
      </SchemaBasedProperties>
    </Properties>
  </ViewAttribute>
  <ViewAttribute
    Name="EchDiscperc"
    PrecisionRule="true"
    EntityAttrName="EchDiscperc"
    EntityUsage="R5extcharges"
    AliasName="ECH_DISCPERC">
    <Properties>
      <SchemaBasedProperties>
        <LABEL
          ResId="its.mnr.mp5.vo.po.POExchargesView.EchDiscperc_LABEL"/>
      </SchemaBasedProperties>
    </Properties>
  </ViewAttribute>
  <ViewAttribute
    Name="EchId"
    IsNotNull="true"
    PrecisionRule="true"
    EntityAttrName="EchId"
    EntityUsage="R5extcharges"
    AliasName="ECH_ID"
    IsUpdateable="while_insert"/>
  <ViewAttribute
    Name="EchInvord"
    PrecisionRule="true"
    EntityAttrName="EchInvord"
    EntityUsage="R5extcharges"
    AliasName="ECH_INVORD"
    DefaultValue="O"/>
  <ViewAttribute
    Name="EchInvordCode"
    PrecisionRule="true"
    EntityAttrName="EchInvordCode"
    EntityUsage="R5extcharges"
    AliasName="ECH_INVORD_CODE">
    <Properties>
      <SchemaBasedProperties>
        <LABEL
          ResId="its.mnr.mp5.vo.po.POExchargesView.EchInvordCode_LABEL"/>
      </SchemaBasedProperties>
    </Properties>
  </ViewAttribute>
  <ViewAttribute
    Name="EchInvordLine"
    PrecisionRule="true"
    EntityAttrName="EchInvordLine"
    EntityUsage="R5extcharges"
    AliasName="ECH_INVORD_LINE">
    <Properties>
      <SchemaBasedProperties>
        <LABEL
          ResId="its.mnr.mp5.vo.po.POExchargesView.EchInvordLine_LABEL"/>
      </SchemaBasedProperties>
    </Properties>
  </ViewAttribute>
  <ViewAttribute
    Name="EchInvordOrg"
    PrecisionRule="true"
    EntityAttrName="EchInvordOrg"
    EntityUsage="R5extcharges"
    AliasName="ECH_INVORD_ORG"/>
  <ViewAttribute
    Name="EchParprice"
    PrecisionRule="true"
    EntityAttrName="EchParprice"
    EntityUsage="R5extcharges"
    AliasName="ECH_PARPRICE"
    DefaultValue="+">
    <Properties>
      <SchemaBasedProperties>
        <LABEL
          ResId="its.mnr.mp5.vo.po.POExchargesView.EchParprice_LABEL"/>
        <CONTROLTYPE
          Value="default"/>
      </SchemaBasedProperties>
    </Properties>
  </ViewAttribute>
  <ViewAttribute
    Name="EchRtype"
    PrecisionRule="true"
    EntityAttrName="EchRtype"
    EntityUsage="R5extcharges"
    AliasName="ECH_RTYPE"
    DefaultValue="*"/>
  <ViewAttribute
    Name="EchType"
    PrecisionRule="true"
    EntityAttrName="EchType"
    EntityUsage="R5extcharges"
    AliasName="ECH_TYPE"
    LOVName="LOV_EchType">
    <Properties>
      <SchemaBasedProperties>
        <LABEL
          ResId="its.mnr.mp5.vo.po.POExchargesView.EchType_LABEL"/>
        <CONTROLTYPE
          Value="choice"/>
      </SchemaBasedProperties>
    </Properties>
  </ViewAttribute>
  <ViewAttribute
    Name="tTypeDesc"
    IsSelected="false"
    IsPersistent="false"
    PrecisionRule="true"
    Type="java.lang.String"
    ColumnType="VARCHAR2"
    AliasName="VIEW_ATTR"
    SQLType="VARCHAR"
    IsQueriable="false">
    <RecalcCondition><![CDATA[true]]></RecalcCondition>
    <TransientExpression><![CDATA[EchType == null || UCodesLOVXchargesType == null ? null : UCodesLOVXchargesType.UcoDesc]]></TransientExpression>
    <Dependencies>
      <Item
        Value="EchType"/>
    </Dependencies>
    <Properties>
      <SchemaBasedProperties>
        <LABEL
          ResId="its.mnr.mp5.vo.po.POExchargesView.tTypeDesc_LABEL"/>
      </SchemaBasedProperties>
    </Properties>
  </ViewAttribute>
  <ViewLinkAccessor
    Name="UCodesLOVXchargesType"
    ViewLink="its.mnr.mp5.vo.link.POExchargesUcodesLovLink"
    Type="oracle.jbo.Row"
    IsUpdateable="false"/>
  <ViewLinkAccessor
    Name="POrderlinesView"
    ViewLink="its.mnr.mp5.vo.link.POOrderlinesExchargesLink"
    Type="oracle.jbo.Row"
    Reversed="true"
    IsUpdateable="false"/>
  <ResourceBundle>
    <PropertiesBundle
      PropertiesFile="its.mnr.mp5.model.ModelBundle"/>
  </ResourceBundle>
</ViewObject>
